passwd_encrypt/__init__.py
passwd_encrypt/passwd_encrypt.py
passwd_encrypt-0.2.4.dist-info/LICENSE
passwd_encrypt-0.2.4.dist-info/METADATA
passwd_encrypt-0.2.4.dist-info/WHEEL
passwd_encrypt-0.2.4.dist-info/top_level.txt
passwd_encrypt-0.2.4.dist-info/RECORD
