Metadata-Version: 2.1
Name: passwd-encrypt
Version: 0.2.4
Summary: A simple tool to generate RSA keys and use them to encrypt/decrypt messages.
Home-page: https://github.com/jrdcasa/passwd-encrypt
Author: Javier Ramos
Author-email: jrdcasa@gmail.com
License: MIT
Download-URL: https://github.com/jrdcasa/passwd-encrypt/archive/refs/tags/v_0.2.1.tar.gz
Platform: UNKNOWN
Classifier: Development Status :: 5 - Production/Stable
Classifier: Intended Audience :: Education
Classifier: Intended Audience :: Science/Research
Classifier: License :: OSI Approved :: MIT License
Classifier: Operating System :: OS Independent
Classifier: Programming Language :: Python
Classifier: Topic :: Scientific/Engineering
License-File: LICENSE
Requires-Dist: pycryptodome
